README.txt
setup.cfg
setup.py
docs/.DS_Store
docs/HISTORY.txt
docs/INSTALL.txt
docs/LICENSE.GPL
docs/LICENSE.txt
medialog/__init__.py
medialog.tinymceplugins.placegallery.egg-info/PKG-INFO
medialog.tinymceplugins.placegallery.egg-info/SOURCES.txt
medialog.tinymceplugins.placegallery.egg-info/dependency_links.txt
medialog.tinymceplugins.placegallery.egg-info/entry_points.txt
medialog.tinymceplugins.placegallery.egg-info/namespace_packages.txt
medialog.tinymceplugins.placegallery.egg-info/not-zip-safe
medialog.tinymceplugins.placegallery.egg-info/requires.txt
medialog.tinymceplugins.placegallery.egg-info/top_level.txt
medialog/tinymceplugins/__init__.py
medialog/tinymceplugins/placegallery/__init__.py
medialog/tinymceplugins/placegallery/configure.zcml
medialog/tinymceplugins/placegallery/tests.py
medialog/tinymceplugins/placegallery/profiles/default/medialog.tinymceplugins.placegallery.txt
medialog/tinymceplugins/placegallery/profiles/default/metadata.xml
medialog/tinymceplugins/placegallery/profiles/default/skins.xml
medialog/tinymceplugins/placegallery/profiles/default/tinymce.xml
medialog/tinymceplugins/placegallery/skins/tinymce_plugin_placegallery/placegallery/dialog.htm.pt
medialog/tinymceplugins/placegallery/skins/tinymce_plugin_placegallery/placegallery/editor_plugin.js
medialog/tinymceplugins/placegallery/skins/tinymce_plugin_placegallery/placegallery/img/placegallery.gif
medialog/tinymceplugins/placegallery/skins/tinymce_plugin_placegallery/placegallery/js/dialog.js
medialog/tinymceplugins/placegallery/skins/tinymce_plugin_placegallery/placegallery/langs/en.js
medialog/tinymceplugins/placegallery/skins/tinymce_plugin_placegallery/placegallery/langs/en_dlg.js