Metadata-Version: 1.0
Name: medialog.tinymceplugins.placegallery
Version: 0.0.2alpha
Summary: An not so advanced TinyMCE plugin for handling links to galleries
Home-page: http://svn.plone.org/svn/collective/medialog.tinymceplugins.placegallery/
Author: Espen Moe-Nilssen
Author-email: espen@medialog.no
License: GPL
Keywords: tinymce plugin gallery link
Platform: UNKNOWN
Classifier: Development Status :: 3 - Alpha
Classifier: Framework :: Plone
Classifier: Programming Language :: Python
Classifier: Programming Language :: JavaScript
